enosfs/__init__.py
enosfs/cli.py
enosfs-0.1.2.dist-info/LICENSE
enosfs-0.1.2.dist-info/METADATA
enosfs-0.1.2.dist-info/WHEEL
enosfs-0.1.2.dist-info/entry_points.txt
enosfs-0.1.2.dist-info/top_level.txt
enosfs-0.1.2.dist-info/RECORD
